<?xml version="1.0" encoding="UTF-8"?>
<!DOCTYPE mapper PUBLIC "-//mybatis.org//DTD Mapper 3.0//EN" "http://mybatis.org/dtd/mybatis-3-mapper.dtd">
<mapper namespace="com.cloud.blog.dao.ContentMapper">
  <resultMap id="BaseResultMap" type="com.cloud.blog.dataObject.Content">
    <!--
      WARNING - @mbg.generated
      This element is automatically generated by MyBatis Generator, do not modify.
      This element was generated on Sat Jan 12 21:33:54 EST 2019.
    -->
    <id column="id" jdbcType="INTEGER" property="id" />
    <result column="createDate" jdbcType="TIMESTAMP" property="createdate" />
    <result column="timestamp" jdbcType="INTEGER" property="timestamp" />
    <result column="content_type" jdbcType="INTEGER" property="contentType" />
    <result column="mapping_id" jdbcType="INTEGER" property="mappingId" />
    <result column="author_id" jdbcType="INTEGER" property="authorId" />
    <result column="like" jdbcType="INTEGER" property="like" />
    <result column="view" jdbcType="INTEGER" property="view" />
  </resultMap>
  <resultMap extends="BaseResultMap" id="ResultMapWithBLOBs" type="com.cloud.blog.dataObject.Content">
    <!--
      WARNING - @mbg.generated
      This element is automatically generated by MyBatis Generator, do not modify.
      This element was generated on Sat Jan 12 21:33:54 EST 2019.
    -->
    <result column="comment" jdbcType="LONGVARCHAR" property="comment"/>
  </resultMap>

  <resultMap id="ResultMapWithAuthor" type="com.cloud.blog.service.model.ContentModel" extends="ResultMapWithBLOBs">
    <result column="nickname" jdbcType="VARCHAR" property="authorName"/>
    <result column="avartar" jdbcType="VARCHAR" property="avatar"/>
  </resultMap>

  <sql id="Base_Column_List">
    <!--
      WARNING - @mbg.generated
      This element is automatically generated by MyBatis Generator, do not modify.
      This element was generated on Sat Jan 12 21:33:54 EST 2019.
    -->
    id, createDate, timestamp, content_type, mapping_id, author_id, like, view
  </sql>
  <sql id="Blob_Column_List">
    <!--
      WARNING - @mbg.generated
      This element is automatically generated by MyBatis Generator, do not modify.
      This element was generated on Sat Jan 12 21:33:54 EST 2019.
    -->
    comment
  </sql>
  <select id="selectByPrimaryKey" parameterType="java.lang.Integer" resultMap="ResultMapWithBLOBs">
    <!--
      WARNING - @mbg.generated
      This element is automatically generated by MyBatis Generator, do not modify.
      This element was generated on Sat Jan 12 21:33:54 EST 2019.
    -->
    select 
    <include refid="Base_Column_List" />
    ,
    <include refid="Blob_Column_List" />
    from content
    where id = #{id,jdbcType=INTEGER}
  </select>

  <select id="getContentByTime" resultMap="ResultMapWithAuthor">
    select content.*, user_info.nickname as nickname, user_info.avartar as avartar
    from content join user_info on content.author_id=user_info.id order by timestamp desc
  </select>

  <select id="getContentByTimeUserId" parameterType="java.lang.Integer" resultMap="ResultMapWithAuthor">
    <!--
      WARNING - @mbg.generated
      This element is automatically generated by MyBatis Generator, do not modify.
      This element was generated on Sat Jan 12 21:33:54 EST 2019.
    -->
    select content.*, user_info.nickname as nickname, user_info.avartar as avartar
    from content join user_info on content.author_id=user_info.id
    where author_id = #{userId,jdbcType=INTEGER} order by timestamp desc
  </select>

  <delete id="deleteByPrimaryKey" parameterType="java.lang.Integer">
    <!--
      WARNING - @mbg.generated
      This element is automatically generated by MyBatis Generator, do not modify.
      This element was generated on Sat Jan 12 21:33:54 EST 2019.
    -->
    delete from content
    where id = #{id,jdbcType=INTEGER}
  </delete>
  <insert id="insert" parameterType="com.cloud.blog.dataObject.Content">
    <!--
      WARNING - @mbg.generated
      This element is automatically generated by MyBatis Generator, do not modify.
      This element was generated on Sat Jan 12 21:33:54 EST 2019.
    -->
    insert into content (id, createDate, timestamp, 
      content_type, mapping_id, author_id, 
      like, view, comment
      )
    values (#{id,jdbcType=INTEGER}, #{createdate,jdbcType=TIMESTAMP}, #{timestamp,jdbcType=INTEGER}, 
      #{contentType,jdbcType=INTEGER}, #{mappingId,jdbcType=INTEGER}, #{authorId,jdbcType=INTEGER}, 
      #{like,jdbcType=INTEGER}, #{view,jdbcType=INTEGER}, #{comment,jdbcType=LONGVARCHAR}
      )
  </insert>
  <insert id="insertSelective" parameterType="com.cloud.blog.dataObject.Content" keyProperty="id" useGeneratedKeys="true">
    <!--
      WARNING - @mbg.generated
      This element is automatically generated by MyBatis Generator, do not modify.
      This element was generated on Sat Jan 12 21:33:54 EST 2019.
    -->
    insert into content
    <trim prefix="(" suffix=")" suffixOverrides=",">
      <if test="id != null">
        id,
      </if>
      <if test="createdate != null">
        createDate,
      </if>
      <if test="timestamp != null">
        timestamp,
      </if>
      <if test="contentType != null">
        content_type,
      </if>
      <if test="mappingId != null">
        mapping_id,
      </if>
      <if test="authorId != null">
        author_id,
      </if>
      <if test="like != null">
        like,
      </if>
      <if test="view != null">
        view,
      </if>
      <if test="comment != null">
        comment,
      </if>
    </trim>
    <trim prefix="values (" suffix=")" suffixOverrides=",">
      <if test="id != null">
        #{id,jdbcType=INTEGER},
      </if>
      <if test="createdate != null">
        #{createdate,jdbcType=TIMESTAMP},
      </if>
      <if test="timestamp != null">
        #{timestamp,jdbcType=INTEGER},
      </if>
      <if test="contentType != null">
        #{contentType,jdbcType=INTEGER},
      </if>
      <if test="mappingId != null">
        #{mappingId,jdbcType=INTEGER},
      </if>
      <if test="authorId != null">
        #{authorId,jdbcType=INTEGER},
      </if>
      <if test="like != null">
        #{like,jdbcType=INTEGER},
      </if>
      <if test="view != null">
        #{view,jdbcType=INTEGER},
      </if>
      <if test="comment != null">
        #{comment,jdbcType=LONGVARCHAR},
      </if>
    </trim>
  </insert>
  <update id="updateByPrimaryKeySelective" parameterType="com.cloud.blog.dataObject.Content">
    <!--
      WARNING - @mbg.generated
      This element is automatically generated by MyBatis Generator, do not modify.
      This element was generated on Sat Jan 12 21:33:54 EST 2019.
    -->
    update content
    <set>
      <if test="createdate != null">
        createDate = #{createdate,jdbcType=TIMESTAMP},
      </if>
      <if test="timestamp != null">
        timestamp = #{timestamp,jdbcType=INTEGER},
      </if>
      <if test="contentType != null">
        content_type = #{contentType,jdbcType=INTEGER},
      </if>
      <if test="mappingId != null">
        mapping_id = #{mappingId,jdbcType=INTEGER},
      </if>
      <if test="authorId != null">
        author_id = #{authorId,jdbcType=INTEGER},
      </if>
      <if test="like != null">
        like = #{like,jdbcType=INTEGER},
      </if>
      <if test="view != null">
        view = #{view,jdbcType=INTEGER},
      </if>
      <if test="comment != null">
        comment = #{comment,jdbcType=LONGVARCHAR},
      </if>
    </set>
    where id = #{id,jdbcType=INTEGER}
  </update>
  <update id="updateByPrimaryKeyWithBLOBs" parameterType="com.cloud.blog.dataObject.Content">
    <!--
      WARNING - @mbg.generated
      This element is automatically generated by MyBatis Generator, do not modify.
      This element was generated on Sat Jan 12 21:33:54 EST 2019.
    -->
    update content
    set createDate = #{createdate,jdbcType=TIMESTAMP},
      timestamp = #{timestamp,jdbcType=INTEGER},
      content_type = #{contentType,jdbcType=INTEGER},
      mapping_id = #{mappingId,jdbcType=INTEGER},
      author_id = #{authorId,jdbcType=INTEGER},
      like = #{like,jdbcType=INTEGER},
      view = #{view,jdbcType=INTEGER},
      comment = #{comment,jdbcType=LONGVARCHAR}
    where id = #{id,jdbcType=INTEGER}
  </update>

  <update id="initializeComment">
    <!--
      WARNING - @mbg.generated
      This element is automatically generated by MyBatis Generator, do not modify.
      This element was generated on Sat Jan 12 21:33:54 EST 2019.
    -->
    update content
    set createDate = #{createdate,jdbcType=TIMESTAMP},
    timestamp = #{timestamp,jdbcType=INTEGER},
    content_type = #{contentType,jdbcType=INTEGER},
    mapping_id = #{mappingId,jdbcType=INTEGER},
    author_id = #{authorId,jdbcType=INTEGER},
    like = #{like,jdbcType=INTEGER},
    view = #{view,jdbcType=INTEGER},
    comment = #{comment,jdbcType=LONGVARCHAR}
    where id = #{id,jdbcType=INTEGER}
  </update>

  <update id="updateByPrimaryKey" parameterType="com.cloud.blog.dataObject.Content">
    <!--
      WARNING - @mbg.generated
      This element is automatically generated by MyBatis Generator, do not modify.
      This element was generated on Sat Jan 12 21:33:54 EST 2019.
    -->
    update content
    set createDate = #{createdate,jdbcType=TIMESTAMP},
      timestamp = #{timestamp,jdbcType=INTEGER},
      content_type = #{contentType,jdbcType=INTEGER},
      mapping_id = #{mappingId,jdbcType=INTEGER},
      author_id = #{authorId,jdbcType=INTEGER},
      like = #{like,jdbcType=INTEGER},
      view = #{view,jdbcType=INTEGER}
    where id = #{id,jdbcType=INTEGER}
  </update>
</mapper>